bbmd_manager/__init__.py
bbmd_manager/audit.py
bbmd_manager/cli.py
bbmd_manager/client.py
bbmd_manager/models.py
bbmd_manager/network.py
ace_bbmd_manager-0.3.5.dist-info/METADATA
ace_bbmd_manager-0.3.5.dist-info/WHEEL
ace_bbmd_manager-0.3.5.dist-info/entry_points.txt
ace_bbmd_manager-0.3.5.dist-info/RECORD
