Metadata-Version: 2.4
Name: ace-bbmd-manager
Version: 0.3.5
Summary: CLI tool for managing BACnet BBMD Broadcast Distribution Tables with audit logging and rollback
Project-URL: Homepage, https://github.com/ACE-IoT-Solutions/ace-bbmd-manager
Project-URL: Repository, https://github.com/ACE-IoT-Solutions/ace-bbmd-manager
Project-URL: Issues, https://github.com/ACE-IoT-Solutions/ace-bbmd-manager/issues
Requires-Python: >=3.8
Requires-Dist: bacpypes3>=0.0.102
Requires-Dist: click>=8.1.8
